jenkins_tools/__init__.py
jenkins_tools/cli.py
jenkins_tools/core.py
jenkins_tools/commands/__init__.py
jenkins_tools/commands/add_job_to_view.py
jenkins_tools/commands/auth.py
jenkins_tools/commands/build.py
jenkins_tools/commands/console.py
jenkins_tools/commands/copy_job.py
jenkins_tools/commands/create_job.py
jenkins_tools/commands/delete_builds.py
jenkins_tools/commands/delete_job.py
jenkins_tools/commands/describe_credentials.py
jenkins_tools/commands/dev_qa.py
jenkins_tools/commands/disable_job.py
jenkins_tools/commands/domain.py
jenkins_tools/commands/enable_job.py
jenkins_tools/commands/get_job.py
jenkins_tools/commands/groovy.py
jenkins_tools/commands/help.py
jenkins_tools/commands/job_diff.py
jenkins_tools/commands/job_status.py
jenkins_tools/commands/list_builds.py
jenkins_tools/commands/list_credentials.py
jenkins_tools/commands/list_jobs.py
jenkins_tools/commands/list_views.py
jenkins_tools/commands/prompt.py
jenkins_tools/commands/stop_builds.py
jenkins_tools/commands/update_job.py
jenkins_tools/commands/gcp/__init__.py
jenkins_tools/commands/gcp/credential.py
jenkins_tools/commands/gcp/gcp_command.py
jenkins_tools/credential_describers/__init__.py
jenkins_tools/credential_describers/azure_credentials.py
jenkins_tools/credential_describers/azure_storage_credentials.py
jenkins_tools/credential_describers/base.py
jenkins_tools/credential_describers/browserstack_credentials.py
jenkins_tools/credential_describers/file_credentials.py
jenkins_tools/credential_describers/gcp_credentials.py
jenkins_tools/credential_describers/gitlab_token_credentials.py
jenkins_tools/credential_describers/ssh_key_credentials.py
jenkins_tools/credential_describers/string_credentials.py
jenkins_tools/credential_describers/username_password_credentials.py
jenkins_tools/docs/examples/add-job-to-view.md
jenkins_tools/docs/examples/auth.md
jenkins_tools/docs/examples/build.md
jenkins_tools/docs/examples/console.md
jenkins_tools/docs/examples/copy-job.md
jenkee-0.5.1.dist-info/METADATA
jenkee-0.5.1.dist-info/WHEEL
jenkee-0.5.1.dist-info/entry_points.txt
jenkee-0.5.1.dist-info/top_level.txt
jenkee-0.5.1.dist-info/RECORD
