Metadata-Version: 2.4
Name: jenkee
Version: 0.5.1
Summary: Jenkins CLI Helper Tools
Author-email: "Ching Yi, Chan" <chingyichan.tw@gmail.com>
License: MIT
Project-URL: Homepage, https://github.com/qrtt1/jenkins-inspector
Project-URL: Repository, https://github.com/qrtt1/jenkins-inspector
Project-URL: Issues, https://github.com/qrtt1/jenkins-inspector/issues
Classifier: Development Status :: 3 - Alpha
Classifier: Intended Audience :: Developers
Classifier: Topic :: Software Development :: Build Tools
Classifier: Programming Language :: Python :: 3
Classifier: Programming Language :: Python :: 3.10
Classifier: Programming Language :: Python :: 3.11
Classifier: Programming Language :: Python :: 3.12
Classifier: Programming Language :: Python :: 3.13
Requires-Python: >=3.10
Requires-Dist: python-dotenv>=1.0.0
Provides-Extra: dev
Requires-Dist: pytest>=7.0; extra == "dev"
Requires-Dist: pytest-cov>=4.0; extra == "dev"
Requires-Dist: pytest-html>=4.0; extra == "dev"
Requires-Dist: testcontainers>=3.7.1; extra == "dev"
Requires-Dist: black>=22.0; extra == "dev"
Requires-Dist: flake8>=5.0; extra == "dev"
Requires-Dist: mypy>=0.990; extra == "dev"
Provides-Extra: release
Requires-Dist: build>=1.0.0; extra == "release"
Requires-Dist: twine>=4.0.0; extra == "release"
